odoo10_addon_product_exception-10.0.1.0.0.99.dev4-py3.8-nspkg.pth
odoo/addons/product_exception/README.rst
odoo/addons/product_exception/__init__.py
odoo/addons/product_exception/__manifest__.py
odoo/addons/product_exception/data/data.xml
odoo/addons/product_exception/demo/product_exception.xml
odoo/addons/product_exception/i18n/product_exception.pot
odoo/addons/product_exception/models/__init__.py
odoo/addons/product_exception/models/exception_rule.py
odoo/addons/product_exception/models/product.py
odoo/addons/product_exception/readme/CONFIGURE.rst
odoo/addons/product_exception/readme/CONTRIBUTORS.rst
odoo/addons/product_exception/readme/CREDITS.rst
odoo/addons/product_exception/readme/DESCRIPTION.rst
odoo/addons/product_exception/readme/ROADMAP.rst
odoo/addons/product_exception/readme/USAGE.rst
odoo/addons/product_exception/static/description/icon.png
odoo/addons/product_exception/static/description/index.html
odoo/addons/product_exception/tests/__init__.py
odoo/addons/product_exception/tests/test_product_exception.py
odoo/addons/product_exception/views/product.xml
odoo10_addon_product_exception-10.0.1.0.0.99.dev4.dist-info/METADATA
odoo10_addon_product_exception-10.0.1.0.0.99.dev4.dist-info/WHEEL
odoo10_addon_product_exception-10.0.1.0.0.99.dev4.dist-info/namespace_packages.txt
odoo10_addon_product_exception-10.0.1.0.0.99.dev4.dist-info/top_level.txt
odoo10_addon_product_exception-10.0.1.0.0.99.dev4.dist-info/RECORD
